tabulicious/__init__.py
tabulicious/version.txt
tabulicious/formats/__init__.py
tabulicious/formats/atlassian.py
tabulicious/formats/base.py
tabulicious/formats/github.py
tabulicious/formats/html.py
tabulicious/formats/markdown.py
tabulicious/formats/plaintext.py
tabulicious-0.5.0.dist-info/METADATA
tabulicious-0.5.0.dist-info/WHEEL
tabulicious-0.5.0.dist-info/top_level.txt
tabulicious-0.5.0.dist-info/zip-safe
tabulicious-0.5.0.dist-info/RECORD
