Metadata-Version: 2.4
Name: tabulicious
Version: 0.5.0
Summary: Simple text-based table formatting for command line and documentation use.
Author: Daniel Sissman
License-Expression: MIT
Project-URL: documentation, https://github.com/bluebinary/tabulicious/blob/main/README.md
Project-URL: changelog, https://github.com/bluebinary/tabulicious/blob/main/CHANGELOG.md
Project-URL: repository, https://github.com/bluebinary/tabulicious
Project-URL: issues, https://github.com/bluebinary/tabulicious/issues
Project-URL: homepage, https://github.com/bluebinary/tabulicious
Keywords: table,tables,data tables,command line tables,text tables,markdown tables,html tables,atlassian/jira tables,github tables
Platform: any
Classifier: Programming Language :: Python :: 3
Classifier: Programming Language :: Python :: 3.10
Classifier: Programming Language :: Python :: 3.11
Classifier: Programming Language :: Python :: 3.12
Classifier: Programming Language :: Python :: 3.13
Requires-Python: >=3.10
Provides-Extra: development
Requires-Dist: black; extra == "development"
Requires-Dist: pytest; extra == "development"
Requires-Dist: pytest-codeblocks; extra == "development"
Requires-Dist: pyflakes; extra == "development"
Provides-Extra: distribution
Requires-Dist: build; extra == "distribution"
Requires-Dist: twine; extra == "distribution"
Requires-Dist: setup; extra == "distribution"
